tapper/__init__.py
tapper/config.py
tapper/py.typed
tapper/trigger_conditions.py
tapper/action/runner.py
tapper/action/wrapper.py
tapper/boot/initializer.py
tapper/boot/tray_icon.py
tapper/boot/tree_transformer.py
tapper/controller/resource_controller.py
tapper/controller/send_processor.py
tapper/controller/keyboard/kb_api.py
tapper/controller/keyboard/kb_linux_evdev_impl.py
tapper/controller/keyboard/kb_win32_winput_impl.py
tapper/controller/mouse/mouse_api.py
tapper/controller/mouse/mouse_win32_winput_impl.py
tapper/controller/window/window_api.py
tapper/controller/window/window_win32_impl.py
tapper/helper/actions.py
tapper/helper/controls.py
tapper/helper/helper_model.py
tapper/helper/img.py
tapper/helper/lang.py
tapper/helper/_util/image.py
tapper/helper/_util/image_fuzz.py
tapper/helper/_util/recorder.py
tapper/helper/_util/repeater.py
tapper/model/constants.py
tapper/model/errors.py
tapper/model/keyboard.py
tapper/model/languages.py
tapper/model/mouse.py
tapper/model/send.py
tapper/model/tap_tree.py
tapper/model/tap_tree_shadow.py
tapper/model/trigger.py
tapper/model/types_.py
tapper/model/window.py
tapper/parser/common.py
tapper/parser/send_parser.py
tapper/parser/trigger_parser.py
tapper/signal/base_listener.py
tapper/signal/signal_processor.py
tapper/signal/wrapper.py
tapper/signal/keyboard/keyboard_listener.py
tapper/signal/keyboard/linux_kb_listener.py
tapper/signal/keyboard/win32_kb_listener.py
tapper/signal/mouse/mouse_listener.py
tapper/signal/mouse/win32_mouse_listener.py
tapper/state/keeper.py
tapper/util/cache.py
tapper/util/datastructs.py
tapper/util/event.py
tapper/util/type_check.py
tapper/util/linux/evdev_common.py
tapper/validation/report.py
tapper-2024.9.4.dist-info/LICENSE
tapper-2024.9.4.dist-info/METADATA
tapper-2024.9.4.dist-info/WHEEL
tapper-2024.9.4.dist-info/top_level.txt
tapper-2024.9.4.dist-info/RECORD
