Metadata-Version: 2.1
Name: tapper
Version: 2024.9.4
Summary: Modern Hotkey and Macro Tool
Author-email: IGalat <author_email@example.com>
License: GNU AFFERO GENERAL PUBLIC LICENSE
Project-URL: Homepage, https://github.com/IGalat/tapper
Classifier: Development Status :: 4 - Beta
Classifier: Programming Language :: Python :: 3
Classifier: Programming Language :: Python :: 3 :: Only
Classifier: Programming Language :: Python :: 3.10
Classifier: Programming Language :: Python :: 3.11
Classifier: Programming Language :: Python :: 3.12
Classifier: Topic :: System :: Monitoring
Classifier: Operating System :: Microsoft :: Windows
Classifier: Operating System :: POSIX
Classifier: Typing :: Typed
Requires-Python: >=3.10
License-File: LICENSE
Requires-Dist: evdev>=1.6.0; sys_platform == "linux"
Requires-Dist: winput>=1.5.0; sys_platform == "win32"
Requires-Dist: pywin32>=305; sys_platform == "win32"
Provides-Extra: all
Requires-Dist: tapper[tray]; extra == "all"
Requires-Dist: tapper[img]; extra == "all"
Provides-Extra: dev
Requires-Dist: tapper[testing]; extra == "dev"
Requires-Dist: build; extra == "dev"
Requires-Dist: twine; extra == "dev"
Provides-Extra: img
Requires-Dist: pillow>=9.4.0; extra == "img"
Requires-Dist: mss>=7.0.1; extra == "img"
Requires-Dist: numpy>=1.24.1; extra == "img"
Requires-Dist: opencv-python>=4.7.0.68; extra == "img"
Provides-Extra: testing
Requires-Dist: tapper[all]; extra == "testing"
Requires-Dist: pytest>=7.1; extra == "testing"
Requires-Dist: pytest-cov>=3; extra == "testing"
Requires-Dist: mypy>=1.9.0; extra == "testing"
Requires-Dist: flake8>=5; extra == "testing"
Requires-Dist: tox>=3.25; extra == "testing"
Requires-Dist: pre-commit>=2.20; extra == "testing"
Provides-Extra: tray
Requires-Dist: pillow>=9.4.0; extra == "tray"
Requires-Dist: pystray>=0.19.4; extra == "tray"
